{
  "version": "PLAN-27-ORC-CAUSAL-TERMINAL-BLOCKERS-V1",
  "deterministic": true,
  "runs": [
    {
      "exclusiveConstructiveRuntimeMs": 24281,
      "assignmentsReached": 69,
      "cycles": 30,
      "stopReason": "NO_VIABLE_ANCHOR",
      "budgetLimitReached": null,
      "sessionFingerprint": "141b777716a42aa1d6360728b3379fa1a1adabdc5b38481b454e27a1619986bf",
      "finalCombinedAssignmentsFingerprint": "14767426cdf98b637ac9305214b2f6400558a489657ffbc3d5cfe6c5ea9324bf",
      "finalValidationResult": "VALID",
      "exactEligibleAnchorCountAtStop": 105,
      "terminalAnchorsScanned": 105,
      "allEligibleAnchorsExhausted": true,
      "terminalBlockerCodeCounts": {
        "NO_HARD_VALID_BRANCH": 103,
        "DEPENDENCY_CONFLICT": 2,
        "COMBINED_INVALID": 2
      },
      "terminalBlockerEvidenceComplete": true,
      "terminalBlockerEvidenceIncompleteAnchorCount": 0,
      "terminalBlockerEvidenceFingerprint": "99d0988091af050cdfd6589cf2a0a8e8d72834fe5c339340c2141bf52f647f64",
      "terminalPrimaryBlockerCodeCounts": {
        "NO_HARD_VALID_BRANCH": 103,
        "DEPENDENCY_CONFLICT": 2
      },
      "terminalDeadEndReasonCounts": {},
      "terminalBlockedAnchorSample": [
        {
          "rank": 1,
          "anchorTaskId": 311,
          "closureTaskCount": 1,
          "searchSpaceFound": true,
          "provisionalWindowCount": 4,
          "branchCount": 4,
          "candidateBranchCount": 0,
          "closureIncompleteBranchCount": 4,
          "hardValidBranchCount": 0,
          "deadEndReasonCounts": {},
          "blockerCodes": [
            "NO_HARD_VALID_BRANCH"
          ],
          "primaryBlockerCode": "NO_HARD_VALID_BRANCH",
          "evidenceComplete": true,
          "attemptDiagnosticsFingerprint": "878145af2e6f19ee0901ebb366879bdb5c833999d84f4f6f861479ea561ac9b0"
        },
        {
          "rank": 2,
          "anchorTaskId": 506,
          "closureTaskCount": 1,
          "searchSpaceFound": true,
          "provisionalWindowCount": 4,
          "branchCount": 4,
          "candidateBranchCount": 0,
          "closureIncompleteBranchCount": 4,
          "hardValidBranchCount": 0,
          "deadEndReasonCounts": {},
          "blockerCodes": [
            "NO_HARD_VALID_BRANCH"
          ],
          "primaryBlockerCode": "NO_HARD_VALID_BRANCH",
          "evidenceComplete": true,
          "attemptDiagnosticsFingerprint": "8177c982f14ac33dec89fe7674f3527216d69bcc98724652e25fe56ecf001985"
        },
        {
          "rank": 3,
          "anchorTaskId": 314,
          "closureTaskCount": 7,
          "searchSpaceFound": true,
          "provisionalWindowCount": 4,
          "branchCount": 4,
          "candidateBranchCount": 0,
          "closureIncompleteBranchCount": 4,
          "hardValidBranchCount": 0,
          "deadEndReasonCounts": {},
          "blockerCodes": [
            "NO_HARD_VALID_BRANCH"
          ],
          "primaryBlockerCode": "NO_HARD_VALID_BRANCH",
          "evidenceComplete": true,
          "attemptDiagnosticsFingerprint": "5276efc8a2941c31e28afec3e968c09b3ac7b16fd35c0d6aa4ede67bd698b402"
        },
        {
          "rank": 4,
          "anchorTaskId": 307,
          "closureTaskCount": 1,
          "searchSpaceFound": true,
          "provisionalWindowCount": 4,
          "branchCount": 4,
          "candidateBranchCount": 0,
          "closureIncompleteBranchCount": 4,
          "hardValidBranchCount": 0,
          "deadEndReasonCounts": {},
          "blockerCodes": [
            "NO_HARD_VALID_BRANCH"
          ],
          "primaryBlockerCode": "NO_HARD_VALID_BRANCH",
          "evidenceComplete": true,
          "attemptDiagnosticsFingerprint": "af75a945434bb1c9fc804e99716086cf57639c8a6b84fd2f06e6e85da0eabc71"
        },
        {
          "rank": 5,
          "anchorTaskId": 310,
          "closureTaskCount": 1,
          "searchSpaceFound": true,
          "provisionalWindowCount": 4,
          "branchCount": 4,
          "candidateBranchCount": 0,
          "closureIncompleteBranchCount": 4,
          "hardValidBranchCount": 0,
          "deadEndReasonCounts": {},
          "blockerCodes": [
            "NO_HARD_VALID_BRANCH"
          ],
          "primaryBlockerCode": "NO_HARD_VALID_BRANCH",
          "evidenceComplete": true,
          "attemptDiagnosticsFingerprint": "d46c8cfbf4ca5a145eeffe5e827a0d5640dff9529f9636fe55b6aedff8ed3ca5"
        },
        {
          "rank": 6,
          "anchorTaskId": 312,
          "closureTaskCount": 1,
          "searchSpaceFound": true,
          "provisionalWindowCount": 4,
          "branchCount": 4,
          "candidateBranchCount": 0,
          "closureIncompleteBranchCount": 4,
          "hardValidBranchCount": 0,
          "deadEndReasonCounts": {},
          "blockerCodes": [
            "NO_HARD_VALID_BRANCH"
          ],
          "primaryBlockerCode": "NO_HARD_VALID_BRANCH",
          "evidenceComplete": true,
          "attemptDiagnosticsFingerprint": "21dd752db8b58bd3156d1dad0ab1ebbf88fea2f83096828f3fd47178062aceac"
        },
        {
          "rank": 7,
          "anchorTaskId": 505,
          "closureTaskCount": 1,
          "searchSpaceFound": true,
          "provisionalWindowCount": 4,
          "branchCount": 4,
          "candidateBranchCount": 0,
          "closureIncompleteBranchCount": 4,
          "hardValidBranchCount": 0,
          "deadEndReasonCounts": {},
          "blockerCodes": [
            "NO_HARD_VALID_BRANCH"
          ],
          "primaryBlockerCode": "NO_HARD_VALID_BRANCH",
          "evidenceComplete": true,
          "attemptDiagnosticsFingerprint": "63f498db13fb7e3de9b559f63f79037f17c7d4398747b73f6061ad5f737961ac"
        },
        {
          "rank": 8,
          "anchorTaskId": 295,
          "closureTaskCount": 2,
          "searchSpaceFound": true,
          "provisionalWindowCount": 3,
          "branchCount": 3,
          "candidateBranchCount": 0,
          "closureIncompleteBranchCount": 3,
          "hardValidBranchCount": 0,
          "deadEndReasonCounts": {},
          "blockerCodes": [
            "NO_HARD_VALID_BRANCH"
          ],
          "primaryBlockerCode": "NO_HARD_VALID_BRANCH",
          "evidenceComplete": true,
          "attemptDiagnosticsFingerprint": "9ca3daf64af57aca70c2899659e8768734ae9b0250c86de26800dff633e181b5"
        },
        {
          "rank": 9,
          "anchorTaskId": 375,
          "closureTaskCount": 2,
          "searchSpaceFound": true,
          "provisionalWindowCount": 3,
          "branchCount": 3,
          "candidateBranchCount": 0,
          "closureIncompleteBranchCount": 3,
          "hardValidBranchCount": 0,
          "deadEndReasonCounts": {},
          "blockerCodes": [
            "NO_HARD_VALID_BRANCH"
          ],
          "primaryBlockerCode": "NO_HARD_VALID_BRANCH",
          "evidenceComplete": true,
          "attemptDiagnosticsFingerprint": "1caa807263fdffc7b99b77a585bd45390d9f68e56fcc9bc7397d82d809af3745"
        },
        {
          "rank": 10,
          "anchorTaskId": 395,
          "closureTaskCount": 2,
          "searchSpaceFound": true,
          "provisionalWindowCount": 3,
          "branchCount": 3,
          "candidateBranchCount": 0,
          "closureIncompleteBranchCount": 3,
          "hardValidBranchCount": 0,
          "deadEndReasonCounts": {},
          "blockerCodes": [
            "NO_HARD_VALID_BRANCH"
          ],
          "primaryBlockerCode": "NO_HARD_VALID_BRANCH",
          "evidenceComplete": true,
          "attemptDiagnosticsFingerprint": "4e3f23e4b6819fced12afcb33392f248bd352ee76a37ede2b727793e3a60c588"
        }
      ],
      "runtimeTelemetry": {
        "sessionRuntimeMs": 24167,
        "assignmentsPerSecond": 2.69,
        "exclusiveConstructiveRuntimeMs": 24281
      },
      "fingerprint": "141b777716a42aa1d6360728b3379fa1a1adabdc5b38481b454e27a1619986bf"
    },
    {
      "exclusiveConstructiveRuntimeMs": 24356,
      "assignmentsReached": 69,
      "cycles": 30,
      "stopReason": "NO_VIABLE_ANCHOR",
      "budgetLimitReached": null,
      "sessionFingerprint": "141b777716a42aa1d6360728b3379fa1a1adabdc5b38481b454e27a1619986bf",
      "finalCombinedAssignmentsFingerprint": "14767426cdf98b637ac9305214b2f6400558a489657ffbc3d5cfe6c5ea9324bf",
      "finalValidationResult": "VALID",
      "exactEligibleAnchorCountAtStop": 105,
      "terminalAnchorsScanned": 105,
      "allEligibleAnchorsExhausted": true,
      "terminalBlockerCodeCounts": {
        "NO_HARD_VALID_BRANCH": 103,
        "DEPENDENCY_CONFLICT": 2,
        "COMBINED_INVALID": 2
      },
      "terminalBlockerEvidenceComplete": true,
      "terminalBlockerEvidenceIncompleteAnchorCount": 0,
      "terminalBlockerEvidenceFingerprint": "99d0988091af050cdfd6589cf2a0a8e8d72834fe5c339340c2141bf52f647f64",
      "terminalPrimaryBlockerCodeCounts": {
        "NO_HARD_VALID_BRANCH": 103,
        "DEPENDENCY_CONFLICT": 2
      },
      "terminalDeadEndReasonCounts": {},
      "terminalBlockedAnchorSample": [
        {
          "rank": 1,
          "anchorTaskId": 311,
          "closureTaskCount": 1,
          "searchSpaceFound": true,
          "provisionalWindowCount": 4,
          "branchCount": 4,
          "candidateBranchCount": 0,
          "closureIncompleteBranchCount": 4,
          "hardValidBranchCount": 0,
          "deadEndReasonCounts": {},
          "blockerCodes": [
            "NO_HARD_VALID_BRANCH"
          ],
          "primaryBlockerCode": "NO_HARD_VALID_BRANCH",
          "evidenceComplete": true,
          "attemptDiagnosticsFingerprint": "878145af2e6f19ee0901ebb366879bdb5c833999d84f4f6f861479ea561ac9b0"
        },
        {
          "rank": 2,
          "anchorTaskId": 506,
          "closureTaskCount": 1,
          "searchSpaceFound": true,
          "provisionalWindowCount": 4,
          "branchCount": 4,
          "candidateBranchCount": 0,
          "closureIncompleteBranchCount": 4,
          "hardValidBranchCount": 0,
          "deadEndReasonCounts": {},
          "blockerCodes": [
            "NO_HARD_VALID_BRANCH"
          ],
          "primaryBlockerCode": "NO_HARD_VALID_BRANCH",
          "evidenceComplete": true,
          "attemptDiagnosticsFingerprint": "8177c982f14ac33dec89fe7674f3527216d69bcc98724652e25fe56ecf001985"
        },
        {
          "rank": 3,
          "anchorTaskId": 314,
          "closureTaskCount": 7,
          "searchSpaceFound": true,
          "provisionalWindowCount": 4,
          "branchCount": 4,
          "candidateBranchCount": 0,
          "closureIncompleteBranchCount": 4,
          "hardValidBranchCount": 0,
          "deadEndReasonCounts": {},
          "blockerCodes": [
            "NO_HARD_VALID_BRANCH"
          ],
          "primaryBlockerCode": "NO_HARD_VALID_BRANCH",
          "evidenceComplete": true,
          "attemptDiagnosticsFingerprint": "5276efc8a2941c31e28afec3e968c09b3ac7b16fd35c0d6aa4ede67bd698b402"
        },
        {
          "rank": 4,
          "anchorTaskId": 307,
          "closureTaskCount": 1,
          "searchSpaceFound": true,
          "provisionalWindowCount": 4,
          "branchCount": 4,
          "candidateBranchCount": 0,
          "closureIncompleteBranchCount": 4,
          "hardValidBranchCount": 0,
          "deadEndReasonCounts": {},
          "blockerCodes": [
            "NO_HARD_VALID_BRANCH"
          ],
          "primaryBlockerCode": "NO_HARD_VALID_BRANCH",
          "evidenceComplete": true,
          "attemptDiagnosticsFingerprint": "af75a945434bb1c9fc804e99716086cf57639c8a6b84fd2f06e6e85da0eabc71"
        },
        {
          "rank": 5,
          "anchorTaskId": 310,
          "closureTaskCount": 1,
          "searchSpaceFound": true,
          "provisionalWindowCount": 4,
          "branchCount": 4,
          "candidateBranchCount": 0,
          "closureIncompleteBranchCount": 4,
          "hardValidBranchCount": 0,
          "deadEndReasonCounts": {},
          "blockerCodes": [
            "NO_HARD_VALID_BRANCH"
          ],
          "primaryBlockerCode": "NO_HARD_VALID_BRANCH",
          "evidenceComplete": true,
          "attemptDiagnosticsFingerprint": "d46c8cfbf4ca5a145eeffe5e827a0d5640dff9529f9636fe55b6aedff8ed3ca5"
        },
        {
          "rank": 6,
          "anchorTaskId": 312,
          "closureTaskCount": 1,
          "searchSpaceFound": true,
          "provisionalWindowCount": 4,
          "branchCount": 4,
          "candidateBranchCount": 0,
          "closureIncompleteBranchCount": 4,
          "hardValidBranchCount": 0,
          "deadEndReasonCounts": {},
          "blockerCodes": [
            "NO_HARD_VALID_BRANCH"
          ],
          "primaryBlockerCode": "NO_HARD_VALID_BRANCH",
          "evidenceComplete": true,
          "attemptDiagnosticsFingerprint": "21dd752db8b58bd3156d1dad0ab1ebbf88fea2f83096828f3fd47178062aceac"
        },
        {
          "rank": 7,
          "anchorTaskId": 505,
          "closureTaskCount": 1,
          "searchSpaceFound": true,
          "provisionalWindowCount": 4,
          "branchCount": 4,
          "candidateBranchCount": 0,
          "closureIncompleteBranchCount": 4,
          "hardValidBranchCount": 0,
          "deadEndReasonCounts": {},
          "blockerCodes": [
            "NO_HARD_VALID_BRANCH"
          ],
          "primaryBlockerCode": "NO_HARD_VALID_BRANCH",
          "evidenceComplete": true,
          "attemptDiagnosticsFingerprint": "63f498db13fb7e3de9b559f63f79037f17c7d4398747b73f6061ad5f737961ac"
        },
        {
          "rank": 8,
          "anchorTaskId": 295,
          "closureTaskCount": 2,
          "searchSpaceFound": true,
          "provisionalWindowCount": 3,
          "branchCount": 3,
          "candidateBranchCount": 0,
          "closureIncompleteBranchCount": 3,
          "hardValidBranchCount": 0,
          "deadEndReasonCounts": {},
          "blockerCodes": [
            "NO_HARD_VALID_BRANCH"
          ],
          "primaryBlockerCode": "NO_HARD_VALID_BRANCH",
          "evidenceComplete": true,
          "attemptDiagnosticsFingerprint": "9ca3daf64af57aca70c2899659e8768734ae9b0250c86de26800dff633e181b5"
        },
        {
          "rank": 9,
          "anchorTaskId": 375,
          "closureTaskCount": 2,
          "searchSpaceFound": true,
          "provisionalWindowCount": 3,
          "branchCount": 3,
          "candidateBranchCount": 0,
          "closureIncompleteBranchCount": 3,
          "hardValidBranchCount": 0,
          "deadEndReasonCounts": {},
          "blockerCodes": [
            "NO_HARD_VALID_BRANCH"
          ],
          "primaryBlockerCode": "NO_HARD_VALID_BRANCH",
          "evidenceComplete": true,
          "attemptDiagnosticsFingerprint": "1caa807263fdffc7b99b77a585bd45390d9f68e56fcc9bc7397d82d809af3745"
        },
        {
          "rank": 10,
          "anchorTaskId": 395,
          "closureTaskCount": 2,
          "searchSpaceFound": true,
          "provisionalWindowCount": 3,
          "branchCount": 3,
          "candidateBranchCount": 0,
          "closureIncompleteBranchCount": 3,
          "hardValidBranchCount": 0,
          "deadEndReasonCounts": {},
          "blockerCodes": [
            "NO_HARD_VALID_BRANCH"
          ],
          "primaryBlockerCode": "NO_HARD_VALID_BRANCH",
          "evidenceComplete": true,
          "attemptDiagnosticsFingerprint": "4e3f23e4b6819fced12afcb33392f248bd352ee76a37ede2b727793e3a60c588"
        }
      ],
      "runtimeTelemetry": {
        "sessionRuntimeMs": 24218,
        "assignmentsPerSecond": 2.684,
        "exclusiveConstructiveRuntimeMs": 24356
      },
      "fingerprint": "141b777716a42aa1d6360728b3379fa1a1adabdc5b38481b454e27a1619986bf"
    }
  ]
}